[
    {
        "idle_start_timestamp": 720.0,
        "idle_duration": 1197.0,
        "idle_x_start": 0.6828643679618835,
        "idle_y_start": 0.749092161655426,
        "driver_idx": 0.0,
        "idle_start_subblock_id": 10.0
    },
    {
        "idle_start_timestamp": 540.0,
        "idle_duration": 302.0,
        "idle_x_start": 0.3521586060523987,
        "idle_y_start": 0.026257529854774475,
        "driver_idx": 1.0,
        "idle_start_subblock_id": 4.0
    },
    {
        "idle_start_timestamp": 1080.0,
        "idle_duration": 341.0,
        "idle_x_start": 0.4257383346557617,
        "idle_y_start": 0.75921630859375,
        "driver_idx": 2.0,
        "idle_start_subblock_id": 7.0
    },
    {
        "idle_start_timestamp": 360.0,
        "idle_duration": 420.0,
        "idle_x_start": 0.36774370074272156,
        "idle_y_start": 0.0805644541978836,
        "driver_idx": 3.0,
        "idle_start_subblock_id": 4.0
    },
    {
        "idle_start_timestamp": 660.0,
        "idle_duration": 849.0,
        "idle_x_start": 0.34449779987335205,
        "idle_y_start": 0.006779268383979797,
        "driver_idx": 4.0,
        "idle_start_subblock_id": 4.0
    },
    {
        "idle_start_timestamp": 840.0,
        "idle_duration": 157.0,
        "idle_x_start": 0.8099880218505859,
        "idle_y_start": 0.1874600648880005,
        "driver_idx": 5.0,
        "idle_start_subblock_id": 12.0
    },
    {
        "idle_start_timestamp": 660.0,
        "idle_duration": 408.0,
        "idle_x_start": 0.6056112051010132,
        "idle_y_start": 0.7471132278442383,
        "driver_idx": 6.0,
        "idle_start_subblock_id": 10.0
    },
    {
        "idle_start_timestamp": 1320.0,
        "idle_duration": 435.0,
        "idle_x_start": 0.980544924736023,
        "idle_y_start": 0.06221657991409302,
        "driver_idx": 7.0,
        "idle_start_subblock_id": 12.0
    },
    {
        "idle_start_timestamp": 1140.0,
        "idle_duration": 761.0,
        "idle_x_start": 0.535882830619812,
        "idle_y_start": 0.5401057004928589,
        "driver_idx": 8.0,
        "idle_start_subblock_id": 10.0
    },
    {
        "idle_start_timestamp": 540.0,
        "idle_duration": 485.0,
        "idle_x_start": 0.5654975771903992,
        "idle_y_start": 0.507736325263977,
        "driver_idx": 9.0,
        "idle_start_subblock_id": 10.0
    },
    {
        "idle_start_timestamp": 480.0,
        "idle_duration": 121.0,
        "idle_x_start": 0.9914345741271973,
        "idle_y_start": 0.8429409265518188,
        "driver_idx": 10.0,
        "idle_start_subblock_id": 15.0
    },
    {
        "idle_start_timestamp": 300.0,
        "idle_duration": 1329.0,
        "idle_x_start": 0.5726796984672546,
        "idle_y_start": 0.12070322036743164,
        "driver_idx": 11.0,
        "idle_start_subblock_id": 8.0
    },
    {
        "idle_start_timestamp": 600.0,
        "idle_duration": 148.0,
        "idle_x_start": 0.1435675024986267,
        "idle_y_start": 0.15510715544223785,
        "driver_idx": 12.0,
        "idle_start_subblock_id": 0.0
    },
    {
        "idle_start_timestamp": 1260.0,
        "idle_duration": 673.0,
        "idle_x_start": 0.6835741400718689,
        "idle_y_start": 0.7174649834632874,
        "driver_idx": 13.0,
        "idle_start_subblock_id": 10.0
    },
    {
        "idle_start_timestamp": 1200.0,
        "idle_duration": 169.0,
        "idle_x_start": 0.4923861622810364,
        "idle_y_start": 0.12450043857097626,
        "driver_idx": 14.0,
        "idle_start_subblock_id": 4.0
    },
    {
        "idle_start_timestamp": 1140.0,
        "idle_duration": 1126.0,
        "idle_x_start": 0.13044320046901703,
        "idle_y_start": 0.777858555316925,
        "driver_idx": 15.0,
        "idle_start_subblock_id": 3.0
    },
    {
        "idle_start_timestamp": 1260.0,
        "idle_duration": 120.0,
        "idle_x_start": 0.9440159201622009,
        "idle_y_start": 0.7053500413894653,
        "driver_idx": 16.0,
        "idle_start_subblock_id": 14.0
    },
    {
        "idle_start_timestamp": 1320.0,
        "idle_duration": 404.0,
        "idle_x_start": 0.7553879618644714,
        "idle_y_start": 0.861641526222229,
        "driver_idx": 17.0,
        "idle_start_subblock_id": 15.0
    },
    {
        "idle_start_timestamp": 960.0,
        "idle_duration": 329.0,
        "idle_x_start": 0.3987281322479248,
        "idle_y_start": 0.7731829881668091,
        "driver_idx": 18.0,
        "idle_start_subblock_id": 7.0
    },
    {
        "idle_start_timestamp": 1380.0,
        "idle_duration": 1074.0,
        "idle_x_start": 0.4874170422554016,
        "idle_y_start": 0.8622459173202515,
        "driver_idx": 19.0,
        "idle_start_subblock_id": 7.0
    },
    {
        "idle_start_timestamp": 600.0,
        "idle_duration": 223.0,
        "idle_x_start": 0.1418677270412445,
        "idle_y_start": 0.670740008354187,
        "driver_idx": 20.0,
        "idle_start_subblock_id": 2.0
    },
    {
        "idle_start_timestamp": 840.0,
        "idle_duration": 1190.0,
        "idle_x_start": 0.6376768350601196,
        "idle_y_start": 0.6342872977256775,
        "driver_idx": 21.0,
        "idle_start_subblock_id": 10.0
    },
    {
        "idle_start_timestamp": 1140.0,
        "idle_duration": 339.0,
        "idle_x_start": 0.2363944947719574,
        "idle_y_start": 0.18623235821723938,
        "driver_idx": 22.0,
        "idle_start_subblock_id": 0.0
    },
    {
        "idle_start_timestamp": 840.0,
        "idle_duration": 194.0,
        "idle_x_start": 0.34902524948120117,
        "idle_y_start": 0.29037177562713623,
        "driver_idx": 23.0,
        "idle_start_subblock_id": 5.0
    },
    {
        "idle_start_timestamp": 540.0,
        "idle_duration": 1440.0,
        "idle_x_start": 0.8116710782051086,
        "idle_y_start": 0.36195605993270874,
        "driver_idx": 24.0,
        "idle_start_subblock_id": 13.0
    },
    {
        "idle_start_timestamp": 1320.0,
        "idle_duration": 132.0,
        "idle_x_start": 0.3095189929008484,
        "idle_y_start": 0.3097347021102905,
        "driver_idx": 25.0,
        "idle_start_subblock_id": 5.0
    },
    {
        "idle_start_timestamp": 960.0,
        "idle_duration": 641.0,
        "idle_x_start": 0.0667799562215805,
        "idle_y_start": 0.915712296962738,
        "driver_idx": 26.0,
        "idle_start_subblock_id": 3.0
    },
    {
        "idle_start_timestamp": 540.0,
        "idle_duration": 764.0,
        "idle_x_start": 0.5191515684127808,
        "idle_y_start": 0.6513504385948181,
        "driver_idx": 27.0,
        "idle_start_subblock_id": 10.0
    },
    {
        "idle_start_timestamp": 420.0,
        "idle_duration": 448.0,
        "idle_x_start": 0.3419244885444641,
        "idle_y_start": 0.2738720178604126,
        "driver_idx": 28.0,
        "idle_start_subblock_id": 5.0
    },
    {
        "idle_start_timestamp": 1260.0,
        "idle_duration": 603.0,
        "idle_x_start": 0.9905350208282471,
        "idle_y_start": 0.5412328839302063,
        "driver_idx": 29.0,
        "idle_start_subblock_id": 14.0
    },
    {
        "idle_start_timestamp": 240.0,
        "idle_duration": 810.0,
        "idle_x_start": 0.5326794385910034,
        "idle_y_start": 0.2269076257944107,
        "driver_idx": 30.0,
        "idle_start_subblock_id": 8.0
    },
    {
        "idle_start_timestamp": 480.0,
        "idle_duration": 453.0,
        "idle_x_start": 0.3713541328907013,
        "idle_y_start": 0.27298665046691895,
        "driver_idx": 31.0,
        "idle_start_subblock_id": 5.0
    },
    {
        "idle_start_timestamp": 780.0,
        "idle_duration": 1091.0,
        "idle_x_start": 0.11958687007427216,
        "idle_y_start": 0.4597782492637634,
        "driver_idx": 32.0,
        "idle_start_subblock_id": 1.0
    },
    {
        "idle_start_timestamp": 1200.0,
        "idle_duration": 154.0,
        "idle_x_start": 0.1147749274969101,
        "idle_y_start": 0.845018744468689,
        "driver_idx": 33.0,
        "idle_start_subblock_id": 3.0
    },
    {
        "idle_start_timestamp": 840.0,
        "idle_duration": 432.0,
        "idle_x_start": 0.892746090888977,
        "idle_y_start": 0.9339916706085205,
        "driver_idx": 34.0,
        "idle_start_subblock_id": 15.0
    },
    {
        "idle_start_timestamp": 240.0,
        "idle_duration": 675.0,
        "idle_x_start": 0.6052437424659729,
        "idle_y_start": 0.19175457954406738,
        "driver_idx": 35.0,
        "idle_start_subblock_id": 8.0
    },
    {
        "idle_start_timestamp": 660.0,
        "idle_duration": 218.0,
        "idle_x_start": 0.40249747037887573,
        "idle_y_start": 0.10994488000869751,
        "driver_idx": 36.0,
        "idle_start_subblock_id": 4.0
    },
    {
        "idle_start_timestamp": 960.0,
        "idle_duration": 718.0,
        "idle_x_start": 0.9050500392913818,
        "idle_y_start": 0.8144134879112244,
        "driver_idx": 37.0,
        "idle_start_subblock_id": 15.0
    },
    {
        "idle_start_timestamp": 1080.0,
        "idle_duration": 645.0,
        "idle_x_start": 0.8417426347732544,
        "idle_y_start": 0.99974125623703,
        "driver_idx": 38.0,
        "idle_start_subblock_id": 15.0
    },
    {
        "idle_start_timestamp": 420.0,
        "idle_duration": 1203.0,
        "idle_x_start": 0.008624613285064697,
        "idle_y_start": 0.39230436086654663,
        "driver_idx": 39.0,
        "idle_start_subblock_id": 1.0
    },
    {
        "idle_start_timestamp": 540.0,
        "idle_duration": 255.0,
        "idle_x_start": 0.7540770769119263,
        "idle_y_start": 0.6878249645233154,
        "driver_idx": 40.0,
        "idle_start_subblock_id": 14.0
    },
    {
        "idle_start_timestamp": 1260.0,
        "idle_duration": 1242.0,
        "idle_x_start": 0.9354907274246216,
        "idle_y_start": 0.9816334247589111,
        "driver_idx": 41.0,
        "idle_start_subblock_id": 15.0
    },
    {
        "idle_start_timestamp": 1320.0,
        "idle_duration": 1222.0,
        "idle_x_start": 0.26851290464401245,
        "idle_y_start": 0.44065338373184204,
        "driver_idx": 42.0,
        "idle_start_subblock_id": 5.0
    },
    {
        "idle_start_timestamp": 660.0,
        "idle_duration": 1204.0,
        "idle_x_start": 0.6173439621925354,
        "idle_y_start": 0.6066586971282959,
        "driver_idx": 43.0,
        "idle_start_subblock_id": 10.0
    },
    {
        "idle_start_timestamp": 660.0,
        "idle_duration": 752.0,
        "idle_x_start": 0.36799341440200806,
        "idle_y_start": 0.47075653076171875,
        "driver_idx": 44.0,
        "idle_start_subblock_id": 5.0
    },
    {
        "idle_start_timestamp": 780.0,
        "idle_duration": 911.0,
        "idle_x_start": 0.6493697762489319,
        "idle_y_start": 0.542693018913269,
        "driver_idx": 45.0,
        "idle_start_subblock_id": 10.0
    },
    {
        "idle_start_timestamp": 1080.0,
        "idle_duration": 401.0,
        "idle_x_start": 0.8566573858261108,
        "idle_y_start": 0.3891206979751587,
        "driver_idx": 46.0,
        "idle_start_subblock_id": 13.0
    },
    {
        "idle_start_timestamp": 420.0,
        "idle_duration": 205.0,
        "idle_x_start": 0.3151574730873108,
        "idle_y_start": 0.2087521106004715,
        "driver_idx": 47.0,
        "idle_start_subblock_id": 4.0
    },
    {
        "idle_start_timestamp": 1200.0,
        "idle_duration": 307.0,
        "idle_x_start": 0.5735410451889038,
        "idle_y_start": 0.29017174243927,
        "driver_idx": 48.0,
        "idle_start_subblock_id": 9.0
    },
    {
        "idle_start_timestamp": 600.0,
        "idle_duration": 538.0,
        "idle_x_start": 0.5985944867134094,
        "idle_y_start": 0.6517119407653809,
        "driver_idx": 49.0,
        "idle_start_subblock_id": 10.0
    },
    {
        "idle_start_timestamp": 960.0,
        "idle_duration": 973.0,
        "idle_x_start": 0.34497183561325073,
        "idle_y_start": 0.49479416012763977,
        "driver_idx": 50.0,
        "idle_start_subblock_id": 5.0
    },
    {
        "idle_start_timestamp": 960.0,
        "idle_duration": 617.0,
        "idle_x_start": 0.08057177066802979,
        "idle_y_start": 0.8260435461997986,
        "driver_idx": 51.0,
        "idle_start_subblock_id": 3.0
    },
    {
        "idle_start_timestamp": 600.0,
        "idle_duration": 453.0,
        "idle_x_start": 0.06424477696418762,
        "idle_y_start": 0.23608991503715515,
        "driver_idx": 52.0,
        "idle_start_subblock_id": 0.0
    },
    {
        "idle_start_timestamp": 780.0,
        "idle_duration": 378.0,
        "idle_x_start": 0.4281102418899536,
        "idle_y_start": 0.7704949378967285,
        "driver_idx": 53.0,
        "idle_start_subblock_id": 7.0
    },
    {
        "idle_start_timestamp": 780.0,
        "idle_duration": 656.0,
        "idle_x_start": 0.45649755001068115,
        "idle_y_start": 0.6450729370117188,
        "driver_idx": 54.0,
        "idle_start_subblock_id": 6.0
    },
    {
        "idle_start_timestamp": 600.0,
        "idle_duration": 506.0,
        "idle_x_start": 0.7778911590576172,
        "idle_y_start": 0.750420093536377,
        "driver_idx": 55.0,
        "idle_start_subblock_id": 15.0
    },
    {
        "idle_start_timestamp": 1260.0,
        "idle_duration": 378.0,
        "idle_x_start": 0.702634334564209,
        "idle_y_start": 0.9429683089256287,
        "driver_idx": 56.0,
        "idle_start_subblock_id": 11.0
    },
    {
        "idle_start_timestamp": 780.0,
        "idle_duration": 140.0,
        "idle_x_start": 0.22763974964618683,
        "idle_y_start": 0.4870877265930176,
        "driver_idx": 57.0,
        "idle_start_subblock_id": 1.0
    },
    {
        "idle_start_timestamp": 660.0,
        "idle_duration": 1440.0,
        "idle_x_start": 0.5994794964790344,
        "idle_y_start": 0.8646122217178345,
        "driver_idx": 58.0,
        "idle_start_subblock_id": 11.0
    },
    {
        "idle_start_timestamp": 660.0,
        "idle_duration": 533.0,
        "idle_x_start": 0.8240749835968018,
        "idle_y_start": 0.6548360586166382,
        "driver_idx": 59.0,
        "idle_start_subblock_id": 14.0
    },
    {
        "idle_start_timestamp": 960.0,
        "idle_duration": 300.0,
        "idle_x_start": 0.9531747102737427,
        "idle_y_start": 0.02814847230911255,
        "driver_idx": 60.0,
        "idle_start_subblock_id": 12.0
    },
    {
        "idle_start_timestamp": 660.0,
        "idle_duration": 1162.0,
        "idle_x_start": 0.8036986589431763,
        "idle_y_start": 0.41908860206604004,
        "driver_idx": 61.0,
        "idle_start_subblock_id": 13.0
    },
    {
        "idle_start_timestamp": 1200.0,
        "idle_duration": 354.0,
        "idle_x_start": 0.4764895439147949,
        "idle_y_start": 0.601884126663208,
        "driver_idx": 62.0,
        "idle_start_subblock_id": 6.0
    },
    {
        "idle_start_timestamp": 480.0,
        "idle_duration": 557.0,
        "idle_x_start": 0.2544151842594147,
        "idle_y_start": 0.11898718774318695,
        "driver_idx": 63.0,
        "idle_start_subblock_id": 4.0
    },
    {
        "idle_start_timestamp": 660.0,
        "idle_duration": 789.0,
        "idle_x_start": 0.7125897407531738,
        "idle_y_start": 0.4022892713546753,
        "driver_idx": 64.0,
        "idle_start_subblock_id": 9.0
    },
    {
        "idle_start_timestamp": 720.0,
        "idle_duration": 129.0,
        "idle_x_start": 0.5761137008666992,
        "idle_y_start": 0.5092290639877319,
        "driver_idx": 65.0,
        "idle_start_subblock_id": 10.0
    },
    {
        "idle_start_timestamp": 480.0,
        "idle_duration": 444.0,
        "idle_x_start": 0.9922544956207275,
        "idle_y_start": 0.483303427696228,
        "driver_idx": 66.0,
        "idle_start_subblock_id": 13.0
    },
    {
        "idle_start_timestamp": 960.0,
        "idle_duration": 470.0,
        "idle_x_start": 0.22195664048194885,
        "idle_y_start": 0.7503864765167236,
        "driver_idx": 67.0,
        "idle_start_subblock_id": 3.0
    },
    {
        "idle_start_timestamp": 480.0,
        "idle_duration": 905.0,
        "idle_x_start": 0.3867259621620178,
        "idle_y_start": 0.4743764400482178,
        "driver_idx": 68.0,
        "idle_start_subblock_id": 5.0
    },
    {
        "idle_start_timestamp": 1140.0,
        "idle_duration": 157.0,
        "idle_x_start": 0.3426763415336609,
        "idle_y_start": 0.03153121471405029,
        "driver_idx": 69.0,
        "idle_start_subblock_id": 4.0
    },
    {
        "idle_start_timestamp": 780.0,
        "idle_duration": 161.0,
        "idle_x_start": 0.7294574975967407,
        "idle_y_start": 0.8238077163696289,
        "driver_idx": 70.0,
        "idle_start_subblock_id": 11.0
    },
    {
        "idle_start_timestamp": 420.0,
        "idle_duration": 479.0,
        "idle_x_start": 0.632515013217926,
        "idle_y_start": 0.5300097465515137,
        "driver_idx": 71.0,
        "idle_start_subblock_id": 10.0
    },
    {
        "idle_start_timestamp": 960.0,
        "idle_duration": 705.0,
        "idle_x_start": 0.8052452802658081,
        "idle_y_start": 0.09546898305416107,
        "driver_idx": 72.0,
        "idle_start_subblock_id": 12.0
    },
    {
        "idle_start_timestamp": 1260.0,
        "idle_duration": 701.0,
        "idle_x_start": 0.6962757706642151,
        "idle_y_start": 0.5718399882316589,
        "driver_idx": 73.0,
        "idle_start_subblock_id": 10.0
    },
    {
        "idle_start_timestamp": 1320.0,
        "idle_duration": 220.0,
        "idle_x_start": 0.16953663527965546,
        "idle_y_start": 0.21144528687000275,
        "driver_idx": 74.0,
        "idle_start_subblock_id": 0.0
    },
    {
        "idle_start_timestamp": 1320.0,
        "idle_duration": 307.0,
        "idle_x_start": 0.2856517434120178,
        "idle_y_start": 0.029368415474891663,
        "driver_idx": 75.0,
        "idle_start_subblock_id": 4.0
    },
    {
        "idle_start_timestamp": 960.0,
        "idle_duration": 173.0,
        "idle_x_start": 0.7091956734657288,
        "idle_y_start": 0.7474958300590515,
        "driver_idx": 76.0,
        "idle_start_subblock_id": 10.0
    },
    {
        "idle_start_timestamp": 840.0,
        "idle_duration": 1440.0,
        "idle_x_start": 0.826998233795166,
        "idle_y_start": 0.053040385246276855,
        "driver_idx": 77.0,
        "idle_start_subblock_id": 12.0
    },
    {
        "idle_start_timestamp": 1140.0,
        "idle_duration": 128.0,
        "idle_x_start": 0.004607498645782471,
        "idle_y_start": 0.041261494159698486,
        "driver_idx": 78.0,
        "idle_start_subblock_id": 0.0
    },
    {
        "idle_start_timestamp": 180.0,
        "idle_duration": 476.0,
        "idle_x_start": 0.22359704971313477,
        "idle_y_start": 0.8806149363517761,
        "driver_idx": 79.0,
        "idle_start_subblock_id": 3.0
    },
    {
        "idle_start_timestamp": 1200.0,
        "idle_duration": 306.0,
        "idle_x_start": 0.43570733070373535,
        "idle_y_start": 0.4437676966190338,
        "driver_idx": 80.0,
        "idle_start_subblock_id": 5.0
    },
    {
        "idle_start_timestamp": 1320.0,
        "idle_duration": 488.0,
        "idle_x_start": 0.9680032134056091,
        "idle_y_start": 0.7999261021614075,
        "driver_idx": 81.0,
        "idle_start_subblock_id": 15.0
    },
    {
        "idle_start_timestamp": 540.0,
        "idle_duration": 256.0,
        "idle_x_start": 0.37471580505371094,
        "idle_y_start": 0.06968492269515991,
        "driver_idx": 82.0,
        "idle_start_subblock_id": 4.0
    },
    {
        "idle_start_timestamp": 300.0,
        "idle_duration": 202.0,
        "idle_x_start": 0.4102141261100769,
        "idle_y_start": 0.3374965786933899,
        "driver_idx": 83.0,
        "idle_start_subblock_id": 5.0
    },
    {
        "idle_start_timestamp": 840.0,
        "idle_duration": 452.0,
        "idle_x_start": 0.929157018661499,
        "idle_y_start": 0.858798623085022,
        "driver_idx": 84.0,
        "idle_start_subblock_id": 15.0
    },
    {
        "idle_start_timestamp": 720.0,
        "idle_duration": 403.0,
        "idle_x_start": 0.62278813123703,
        "idle_y_start": 0.13302278518676758,
        "driver_idx": 85.0,
        "idle_start_subblock_id": 8.0
    },
    {
        "idle_start_timestamp": 600.0,
        "idle_duration": 302.0,
        "idle_x_start": 0.15926766395568848,
        "idle_y_start": 0.4961414039134979,
        "driver_idx": 86.0,
        "idle_start_subblock_id": 1.0
    },
    {
        "idle_start_timestamp": 1080.0,
        "idle_duration": 454.0,
        "idle_x_start": 0.5024666786193848,
        "idle_y_start": 0.38618695735931396,
        "driver_idx": 87.0,
        "idle_start_subblock_id": 9.0
    },
    {
        "idle_start_timestamp": 1140.0,
        "idle_duration": 261.0,
        "idle_x_start": 0.6240124702453613,
        "idle_y_start": 0.6165250539779663,
        "driver_idx": 88.0,
        "idle_start_subblock_id": 10.0
    },
    {
        "idle_start_timestamp": 60.0,
        "idle_duration": 760.0,
        "idle_x_start": 0.05596409738063812,
        "idle_y_start": 0.6098384261131287,
        "driver_idx": 89.0,
        "idle_start_subblock_id": 2.0
    },
    {
        "idle_start_timestamp": 1020.0,
        "idle_duration": 840.0,
        "idle_x_start": 0.6655302047729492,
        "idle_y_start": 0.9842267632484436,
        "driver_idx": 90.0,
        "idle_start_subblock_id": 11.0
    },
    {
        "idle_start_timestamp": 660.0,
        "idle_duration": 255.0,
        "idle_x_start": 0.9243423938751221,
        "idle_y_start": 0.6050249338150024,
        "driver_idx": 91.0,
        "idle_start_subblock_id": 14.0
    },
    {
        "idle_start_timestamp": 1020.0,
        "idle_duration": 293.0,
        "idle_x_start": 0.40715983510017395,
        "idle_y_start": 0.7303009629249573,
        "driver_idx": 92.0,
        "idle_start_subblock_id": 6.0
    },
    {
        "idle_start_timestamp": 480.0,
        "idle_duration": 501.0,
        "idle_x_start": 0.9547706842422485,
        "idle_y_start": 0.40211713314056396,
        "driver_idx": 93.0,
        "idle_start_subblock_id": 13.0
    },
    {
        "idle_start_timestamp": 660.0,
        "idle_duration": 1315.0,
        "idle_x_start": 0.03064444661140442,
        "idle_y_start": 0.6257504224777222,
        "driver_idx": 94.0,
        "idle_start_subblock_id": 2.0
    },
    {
        "idle_start_timestamp": 360.0,
        "idle_duration": 164.0,
        "idle_x_start": 0.9008593559265137,
        "idle_y_start": 0.5171607732772827,
        "driver_idx": 95.0,
        "idle_start_subblock_id": 14.0
    },
    {
        "idle_start_timestamp": 1020.0,
        "idle_duration": 1299.0,
        "idle_x_start": 0.07448707520961761,
        "idle_y_start": 0.7939835786819458,
        "driver_idx": 96.0,
        "idle_start_subblock_id": 3.0
    },
    {
        "idle_start_timestamp": 1020.0,
        "idle_duration": 416.0,
        "idle_x_start": 0.0574769526720047,
        "idle_y_start": 0.570745050907135,
        "driver_idx": 97.0,
        "idle_start_subblock_id": 2.0
    },
    {
        "idle_start_timestamp": 600.0,
        "idle_duration": 490.0,
        "idle_x_start": 0.6977643370628357,
        "idle_y_start": 0.02883976697921753,
        "driver_idx": 98.0,
        "idle_start_subblock_id": 8.0
    },
    {
        "idle_start_timestamp": 840.0,
        "idle_duration": 855.0,
        "idle_x_start": 0.9369297027587891,
        "idle_y_start": 0.2851506173610687,
        "driver_idx": 99.0,
        "idle_start_subblock_id": 13.0
    }
]