[
    {
        "idle_start_timestamp": 960.0,
        "idle_duration": 132.0,
        "idle_x_start": 0.9946261644363403,
        "idle_y_start": 0.4341296851634979,
        "driver_idx": 0.0,
        "idle_start_subblock_id": 13.0
    },
    {
        "idle_start_timestamp": 780.0,
        "idle_duration": 708.0,
        "idle_x_start": 0.8655102849006653,
        "idle_y_start": 0.02578379213809967,
        "driver_idx": 1.0,
        "idle_start_subblock_id": 12.0
    },
    {
        "idle_start_timestamp": 1260.0,
        "idle_duration": 240.0,
        "idle_x_start": 0.08442744612693787,
        "idle_y_start": 0.5524864792823792,
        "driver_idx": 2.0,
        "idle_start_subblock_id": 2.0
    },
    {
        "idle_start_timestamp": 960.0,
        "idle_duration": 819.0,
        "idle_x_start": 0.21885813772678375,
        "idle_y_start": 0.7695789933204651,
        "driver_idx": 3.0,
        "idle_start_subblock_id": 3.0
    },
    {
        "idle_start_timestamp": 1380.0,
        "idle_duration": 158.0,
        "idle_x_start": 0.1621636152267456,
        "idle_y_start": 0.03303542733192444,
        "driver_idx": 4.0,
        "idle_start_subblock_id": 0.0
    },
    {
        "idle_start_timestamp": 180.0,
        "idle_duration": 698.0,
        "idle_x_start": 0.450786828994751,
        "idle_y_start": 0.46039146184921265,
        "driver_idx": 5.0,
        "idle_start_subblock_id": 5.0
    },
    {
        "idle_start_timestamp": 540.0,
        "idle_duration": 147.0,
        "idle_x_start": 0.04838098585605621,
        "idle_y_start": 0.4862198829650879,
        "driver_idx": 6.0,
        "idle_start_subblock_id": 1.0
    },
    {
        "idle_start_timestamp": 600.0,
        "idle_duration": 378.0,
        "idle_x_start": 0.44376564025878906,
        "idle_y_start": 0.5558686256408691,
        "driver_idx": 7.0,
        "idle_start_subblock_id": 6.0
    },
    {
        "idle_start_timestamp": 660.0,
        "idle_duration": 695.0,
        "idle_x_start": 0.7036947011947632,
        "idle_y_start": 0.7381817698478699,
        "driver_idx": 8.0,
        "idle_start_subblock_id": 10.0
    },
    {
        "idle_start_timestamp": 660.0,
        "idle_duration": 528.0,
        "idle_x_start": 0.24045710265636444,
        "idle_y_start": 0.03496958315372467,
        "driver_idx": 9.0,
        "idle_start_subblock_id": 0.0
    },
    {
        "idle_start_timestamp": 720.0,
        "idle_duration": 1426.0,
        "idle_x_start": 0.0035950690507888794,
        "idle_y_start": 0.43874436616897583,
        "driver_idx": 10.0,
        "idle_start_subblock_id": 1.0
    },
    {
        "idle_start_timestamp": 540.0,
        "idle_duration": 994.0,
        "idle_x_start": 0.2948046922683716,
        "idle_y_start": 0.9823387861251831,
        "driver_idx": 11.0,
        "idle_start_subblock_id": 7.0
    },
    {
        "idle_start_timestamp": 720.0,
        "idle_duration": 832.0,
        "idle_x_start": 0.2677229940891266,
        "idle_y_start": 0.42362433671951294,
        "driver_idx": 12.0,
        "idle_start_subblock_id": 5.0
    },
    {
        "idle_start_timestamp": 840.0,
        "idle_duration": 494.0,
        "idle_x_start": 0.44013601541519165,
        "idle_y_start": 0.921971321105957,
        "driver_idx": 13.0,
        "idle_start_subblock_id": 7.0
    },
    {
        "idle_start_timestamp": 360.0,
        "idle_duration": 785.0,
        "idle_x_start": 0.9250805377960205,
        "idle_y_start": 0.5486705899238586,
        "driver_idx": 14.0,
        "idle_start_subblock_id": 14.0
    },
    {
        "idle_start_timestamp": 1380.0,
        "idle_duration": 176.0,
        "idle_x_start": 0.0503658801317215,
        "idle_y_start": 0.7221215963363647,
        "driver_idx": 15.0,
        "idle_start_subblock_id": 2.0
    },
    {
        "idle_start_timestamp": 1080.0,
        "idle_duration": 268.0,
        "idle_x_start": 0.8594313859939575,
        "idle_y_start": 0.37914231419563293,
        "driver_idx": 16.0,
        "idle_start_subblock_id": 13.0
    },
    {
        "idle_start_timestamp": 480.0,
        "idle_duration": 291.0,
        "idle_x_start": 0.7473993301391602,
        "idle_y_start": 0.47470855712890625,
        "driver_idx": 17.0,
        "idle_start_subblock_id": 9.0
    },
    {
        "idle_start_timestamp": 1320.0,
        "idle_duration": 1440.0,
        "idle_x_start": 0.2402401566505432,
        "idle_y_start": 0.36175957322120667,
        "driver_idx": 18.0,
        "idle_start_subblock_id": 1.0
    },
    {
        "idle_start_timestamp": 1140.0,
        "idle_duration": 526.0,
        "idle_x_start": 0.22747235000133514,
        "idle_y_start": 0.7171058058738708,
        "driver_idx": 19.0,
        "idle_start_subblock_id": 2.0
    },
    {
        "idle_start_timestamp": 1200.0,
        "idle_duration": 560.0,
        "idle_x_start": 0.44570448994636536,
        "idle_y_start": 0.8728954792022705,
        "driver_idx": 20.0,
        "idle_start_subblock_id": 7.0
    },
    {
        "idle_start_timestamp": 1140.0,
        "idle_duration": 1298.0,
        "idle_x_start": 0.29186612367630005,
        "idle_y_start": 0.6357681155204773,
        "driver_idx": 21.0,
        "idle_start_subblock_id": 6.0
    },
    {
        "idle_start_timestamp": 1020.0,
        "idle_duration": 289.0,
        "idle_x_start": 0.3631748557090759,
        "idle_y_start": 0.9561700820922852,
        "driver_idx": 22.0,
        "idle_start_subblock_id": 7.0
    },
    {
        "idle_start_timestamp": 780.0,
        "idle_duration": 205.0,
        "idle_x_start": 0.9837150573730469,
        "idle_y_start": 0.8332710266113281,
        "driver_idx": 23.0,
        "idle_start_subblock_id": 15.0
    },
    {
        "idle_start_timestamp": 540.0,
        "idle_duration": 120.0,
        "idle_x_start": 0.6395925283432007,
        "idle_y_start": 0.2804993987083435,
        "driver_idx": 24.0,
        "idle_start_subblock_id": 9.0
    },
    {
        "idle_start_timestamp": 1260.0,
        "idle_duration": 668.0,
        "idle_x_start": 0.01570408046245575,
        "idle_y_start": 0.15870103240013123,
        "driver_idx": 25.0,
        "idle_start_subblock_id": 0.0
    },
    {
        "idle_start_timestamp": 600.0,
        "idle_duration": 305.0,
        "idle_x_start": 0.9879821538925171,
        "idle_y_start": 0.3087942898273468,
        "driver_idx": 26.0,
        "idle_start_subblock_id": 13.0
    },
    {
        "idle_start_timestamp": 960.0,
        "idle_duration": 442.0,
        "idle_x_start": 0.9281792640686035,
        "idle_y_start": 0.7565707564353943,
        "driver_idx": 27.0,
        "idle_start_subblock_id": 15.0
    },
    {
        "idle_start_timestamp": 660.0,
        "idle_duration": 251.0,
        "idle_x_start": 0.7013862133026123,
        "idle_y_start": 0.6765149235725403,
        "driver_idx": 28.0,
        "idle_start_subblock_id": 10.0
    },
    {
        "idle_start_timestamp": 840.0,
        "idle_duration": 416.0,
        "idle_x_start": 0.3971121609210968,
        "idle_y_start": 0.22724094986915588,
        "driver_idx": 29.0,
        "idle_start_subblock_id": 4.0
    },
    {
        "idle_start_timestamp": 480.0,
        "idle_duration": 143.0,
        "idle_x_start": 0.8974303007125854,
        "idle_y_start": 0.7556202411651611,
        "driver_idx": 30.0,
        "idle_start_subblock_id": 15.0
    },
    {
        "idle_start_timestamp": 840.0,
        "idle_duration": 546.0,
        "idle_x_start": 0.6623849868774414,
        "idle_y_start": 0.20311497151851654,
        "driver_idx": 31.0,
        "idle_start_subblock_id": 8.0
    },
    {
        "idle_start_timestamp": 1020.0,
        "idle_duration": 203.0,
        "idle_x_start": 0.6830539703369141,
        "idle_y_start": 0.5629679560661316,
        "driver_idx": 32.0,
        "idle_start_subblock_id": 10.0
    },
    {
        "idle_start_timestamp": 420.0,
        "idle_duration": 255.0,
        "idle_x_start": 0.7122349143028259,
        "idle_y_start": 0.024622485041618347,
        "driver_idx": 33.0,
        "idle_start_subblock_id": 8.0
    },
    {
        "idle_start_timestamp": 1020.0,
        "idle_duration": 209.0,
        "idle_x_start": 0.6238569617271423,
        "idle_y_start": 0.5025745630264282,
        "driver_idx": 34.0,
        "idle_start_subblock_id": 10.0
    },
    {
        "idle_start_timestamp": 1080.0,
        "idle_duration": 248.0,
        "idle_x_start": 0.8381542563438416,
        "idle_y_start": 0.9257946014404297,
        "driver_idx": 35.0,
        "idle_start_subblock_id": 15.0
    },
    {
        "idle_start_timestamp": 660.0,
        "idle_duration": 392.0,
        "idle_x_start": 0.022524356842041016,
        "idle_y_start": 0.45988571643829346,
        "driver_idx": 36.0,
        "idle_start_subblock_id": 1.0
    },
    {
        "idle_start_timestamp": 960.0,
        "idle_duration": 1440.0,
        "idle_x_start": 0.10155341029167175,
        "idle_y_start": 0.5257976055145264,
        "driver_idx": 37.0,
        "idle_start_subblock_id": 2.0
    },
    {
        "idle_start_timestamp": 1320.0,
        "idle_duration": 1035.0,
        "idle_x_start": 0.38457930088043213,
        "idle_y_start": 0.828336775302887,
        "driver_idx": 38.0,
        "idle_start_subblock_id": 7.0
    },
    {
        "idle_start_timestamp": 660.0,
        "idle_duration": 178.0,
        "idle_x_start": 0.3933103680610657,
        "idle_y_start": 0.9105339646339417,
        "driver_idx": 39.0,
        "idle_start_subblock_id": 7.0
    },
    {
        "idle_start_timestamp": 420.0,
        "idle_duration": 961.0,
        "idle_x_start": 0.7116795182228088,
        "idle_y_start": 0.9251741170883179,
        "driver_idx": 40.0,
        "idle_start_subblock_id": 11.0
    },
    {
        "idle_start_timestamp": 600.0,
        "idle_duration": 167.0,
        "idle_x_start": 0.9707825183868408,
        "idle_y_start": 0.15094546973705292,
        "driver_idx": 41.0,
        "idle_start_subblock_id": 12.0
    },
    {
        "idle_start_timestamp": 420.0,
        "idle_duration": 157.0,
        "idle_x_start": 0.3342301845550537,
        "idle_y_start": 0.5583578944206238,
        "driver_idx": 42.0,
        "idle_start_subblock_id": 6.0
    },
    {
        "idle_start_timestamp": 720.0,
        "idle_duration": 965.0,
        "idle_x_start": 0.3750687837600708,
        "idle_y_start": 0.856095016002655,
        "driver_idx": 43.0,
        "idle_start_subblock_id": 7.0
    },
    {
        "idle_start_timestamp": 1080.0,
        "idle_duration": 277.0,
        "idle_x_start": 0.46389567852020264,
        "idle_y_start": 0.6840196847915649,
        "driver_idx": 44.0,
        "idle_start_subblock_id": 6.0
    },
    {
        "idle_start_timestamp": 600.0,
        "idle_duration": 212.0,
        "idle_x_start": 0.03213660418987274,
        "idle_y_start": 0.40155112743377686,
        "driver_idx": 45.0,
        "idle_start_subblock_id": 1.0
    },
    {
        "idle_start_timestamp": 1140.0,
        "idle_duration": 156.0,
        "idle_x_start": 0.6446395516395569,
        "idle_y_start": 0.23865646123886108,
        "driver_idx": 46.0,
        "idle_start_subblock_id": 8.0
    },
    {
        "idle_start_timestamp": 1320.0,
        "idle_duration": 638.0,
        "idle_x_start": 0.6741561889648438,
        "idle_y_start": 0.9201061129570007,
        "driver_idx": 47.0,
        "idle_start_subblock_id": 11.0
    },
    {
        "idle_start_timestamp": 1020.0,
        "idle_duration": 211.0,
        "idle_x_start": 0.03346771001815796,
        "idle_y_start": 0.7031254768371582,
        "driver_idx": 48.0,
        "idle_start_subblock_id": 2.0
    },
    {
        "idle_start_timestamp": 480.0,
        "idle_duration": 143.0,
        "idle_x_start": 0.18921653926372528,
        "idle_y_start": 0.4350557029247284,
        "driver_idx": 49.0,
        "idle_start_subblock_id": 1.0
    },
    {
        "idle_start_timestamp": 180.0,
        "idle_duration": 362.0,
        "idle_x_start": 0.9406179785728455,
        "idle_y_start": 0.142239049077034,
        "driver_idx": 50.0,
        "idle_start_subblock_id": 12.0
    },
    {
        "idle_start_timestamp": 1140.0,
        "idle_duration": 407.0,
        "idle_x_start": 0.5928385257720947,
        "idle_y_start": 0.9169050455093384,
        "driver_idx": 51.0,
        "idle_start_subblock_id": 11.0
    },
    {
        "idle_start_timestamp": 900.0,
        "idle_duration": 186.0,
        "idle_x_start": 0.1986362785100937,
        "idle_y_start": 0.03586524724960327,
        "driver_idx": 52.0,
        "idle_start_subblock_id": 0.0
    },
    {
        "idle_start_timestamp": 720.0,
        "idle_duration": 169.0,
        "idle_x_start": 0.37232327461242676,
        "idle_y_start": 0.43397256731987,
        "driver_idx": 53.0,
        "idle_start_subblock_id": 5.0
    },
    {
        "idle_start_timestamp": 840.0,
        "idle_duration": 247.0,
        "idle_x_start": 0.4399651885032654,
        "idle_y_start": 0.797866702079773,
        "driver_idx": 54.0,
        "idle_start_subblock_id": 7.0
    },
    {
        "idle_start_timestamp": 840.0,
        "idle_duration": 1058.0,
        "idle_x_start": 0.7520471215248108,
        "idle_y_start": 0.6512242555618286,
        "driver_idx": 55.0,
        "idle_start_subblock_id": 14.0
    },
    {
        "idle_start_timestamp": 840.0,
        "idle_duration": 346.0,
        "idle_x_start": 0.6915706992149353,
        "idle_y_start": 0.22291439771652222,
        "driver_idx": 56.0,
        "idle_start_subblock_id": 8.0
    },
    {
        "idle_start_timestamp": 1320.0,
        "idle_duration": 991.0,
        "idle_x_start": 0.3223077654838562,
        "idle_y_start": 0.5296316146850586,
        "driver_idx": 57.0,
        "idle_start_subblock_id": 6.0
    },
    {
        "idle_start_timestamp": 120.0,
        "idle_duration": 1440.0,
        "idle_x_start": 0.9944278597831726,
        "idle_y_start": 0.5668753385543823,
        "driver_idx": 58.0,
        "idle_start_subblock_id": 14.0
    },
    {
        "idle_start_timestamp": 600.0,
        "idle_duration": 145.0,
        "idle_x_start": 0.7631940841674805,
        "idle_y_start": 0.3951713442802429,
        "driver_idx": 59.0,
        "idle_start_subblock_id": 13.0
    },
    {
        "idle_start_timestamp": 900.0,
        "idle_duration": 872.0,
        "idle_x_start": 0.9142840504646301,
        "idle_y_start": 0.8151866793632507,
        "driver_idx": 60.0,
        "idle_start_subblock_id": 15.0
    },
    {
        "idle_start_timestamp": 960.0,
        "idle_duration": 337.0,
        "idle_x_start": 0.2656554877758026,
        "idle_y_start": 0.9500072002410889,
        "driver_idx": 61.0,
        "idle_start_subblock_id": 7.0
    },
    {
        "idle_start_timestamp": 1080.0,
        "idle_duration": 156.0,
        "idle_x_start": 0.2671769857406616,
        "idle_y_start": 0.3034409284591675,
        "driver_idx": 62.0,
        "idle_start_subblock_id": 5.0
    },
    {
        "idle_start_timestamp": 1080.0,
        "idle_duration": 394.0,
        "idle_x_start": 0.3149545192718506,
        "idle_y_start": 0.7947723269462585,
        "driver_idx": 63.0,
        "idle_start_subblock_id": 7.0
    },
    {
        "idle_start_timestamp": 420.0,
        "idle_duration": 406.0,
        "idle_x_start": 0.16152943670749664,
        "idle_y_start": 0.603453516960144,
        "driver_idx": 64.0,
        "idle_start_subblock_id": 2.0
    },
    {
        "idle_start_timestamp": 480.0,
        "idle_duration": 180.0,
        "idle_x_start": 0.3338976502418518,
        "idle_y_start": 0.33538269996643066,
        "driver_idx": 65.0,
        "idle_start_subblock_id": 5.0
    },
    {
        "idle_start_timestamp": 480.0,
        "idle_duration": 560.0,
        "idle_x_start": 0.9876970052719116,
        "idle_y_start": 0.8220645785331726,
        "driver_idx": 66.0,
        "idle_start_subblock_id": 15.0
    },
    {
        "idle_start_timestamp": 540.0,
        "idle_duration": 415.0,
        "idle_x_start": 0.6923632025718689,
        "idle_y_start": 0.7911534309387207,
        "driver_idx": 67.0,
        "idle_start_subblock_id": 11.0
    },
    {
        "idle_start_timestamp": 720.0,
        "idle_duration": 378.0,
        "idle_x_start": 0.31316453218460083,
        "idle_y_start": 0.26248735189437866,
        "driver_idx": 68.0,
        "idle_start_subblock_id": 5.0
    },
    {
        "idle_start_timestamp": 720.0,
        "idle_duration": 154.0,
        "idle_x_start": 0.5717291831970215,
        "idle_y_start": 0.08937348425388336,
        "driver_idx": 69.0,
        "idle_start_subblock_id": 8.0
    },
    {
        "idle_start_timestamp": 900.0,
        "idle_duration": 457.0,
        "idle_x_start": 0.6998346447944641,
        "idle_y_start": 0.7071497440338135,
        "driver_idx": 70.0,
        "idle_start_subblock_id": 10.0
    },
    {
        "idle_start_timestamp": 840.0,
        "idle_duration": 340.0,
        "idle_x_start": 0.15503528714179993,
        "idle_y_start": 0.8200843334197998,
        "driver_idx": 71.0,
        "idle_start_subblock_id": 3.0
    },
    {
        "idle_start_timestamp": 720.0,
        "idle_duration": 367.0,
        "idle_x_start": 0.12704721093177795,
        "idle_y_start": 0.27626413106918335,
        "driver_idx": 72.0,
        "idle_start_subblock_id": 1.0
    },
    {
        "idle_start_timestamp": 60.0,
        "idle_duration": 360.0,
        "idle_x_start": 0.6071067452430725,
        "idle_y_start": 0.05150289833545685,
        "driver_idx": 73.0,
        "idle_start_subblock_id": 8.0
    },
    {
        "idle_start_timestamp": 840.0,
        "idle_duration": 1440.0,
        "idle_x_start": 0.6723757982254028,
        "idle_y_start": 0.07609343528747559,
        "driver_idx": 74.0,
        "idle_start_subblock_id": 8.0
    },
    {
        "idle_start_timestamp": 840.0,
        "idle_duration": 905.0,
        "idle_x_start": 0.6353886723518372,
        "idle_y_start": 0.4264650344848633,
        "driver_idx": 75.0,
        "idle_start_subblock_id": 9.0
    },
    {
        "idle_start_timestamp": 480.0,
        "idle_duration": 1440.0,
        "idle_x_start": 0.3717966675758362,
        "idle_y_start": 0.5150943994522095,
        "driver_idx": 76.0,
        "idle_start_subblock_id": 6.0
    },
    {
        "idle_start_timestamp": 480.0,
        "idle_duration": 287.0,
        "idle_x_start": 0.1753685027360916,
        "idle_y_start": 0.7465119361877441,
        "driver_idx": 77.0,
        "idle_start_subblock_id": 2.0
    },
    {
        "idle_start_timestamp": 1140.0,
        "idle_duration": 426.0,
        "idle_x_start": 0.2824209928512573,
        "idle_y_start": 0.5630879998207092,
        "driver_idx": 78.0,
        "idle_start_subblock_id": 6.0
    },
    {
        "idle_start_timestamp": 240.0,
        "idle_duration": 408.0,
        "idle_x_start": 0.39934322237968445,
        "idle_y_start": 0.5966361165046692,
        "driver_idx": 79.0,
        "idle_start_subblock_id": 6.0
    },
    {
        "idle_start_timestamp": 1380.0,
        "idle_duration": 319.0,
        "idle_x_start": 0.13451310992240906,
        "idle_y_start": 0.19416292011737823,
        "driver_idx": 80.0,
        "idle_start_subblock_id": 0.0
    },
    {
        "idle_start_timestamp": 1320.0,
        "idle_duration": 401.0,
        "idle_x_start": 0.7616680860519409,
        "idle_y_start": 0.12643034756183624,
        "driver_idx": 81.0,
        "idle_start_subblock_id": 12.0
    },
    {
        "idle_start_timestamp": 180.0,
        "idle_duration": 489.0,
        "idle_x_start": 0.5671113133430481,
        "idle_y_start": 0.02860216796398163,
        "driver_idx": 82.0,
        "idle_start_subblock_id": 8.0
    },
    {
        "idle_start_timestamp": 1260.0,
        "idle_duration": 837.0,
        "idle_x_start": 0.42504793405532837,
        "idle_y_start": 0.9905335307121277,
        "driver_idx": 83.0,
        "idle_start_subblock_id": 7.0
    },
    {
        "idle_start_timestamp": 900.0,
        "idle_duration": 1440.0,
        "idle_x_start": 0.36626219749450684,
        "idle_y_start": 0.645564615726471,
        "driver_idx": 84.0,
        "idle_start_subblock_id": 6.0
    },
    {
        "idle_start_timestamp": 540.0,
        "idle_duration": 1000.0,
        "idle_x_start": 0.4971523582935333,
        "idle_y_start": 0.5672317743301392,
        "driver_idx": 85.0,
        "idle_start_subblock_id": 6.0
    },
    {
        "idle_start_timestamp": 900.0,
        "idle_duration": 120.0,
        "idle_x_start": 0.8960127830505371,
        "idle_y_start": 0.31560197472572327,
        "driver_idx": 86.0,
        "idle_start_subblock_id": 13.0
    },
    {
        "idle_start_timestamp": 540.0,
        "idle_duration": 392.0,
        "idle_x_start": 0.3050275444984436,
        "idle_y_start": 0.8370965719223022,
        "driver_idx": 87.0,
        "idle_start_subblock_id": 7.0
    },
    {
        "idle_start_timestamp": 1020.0,
        "idle_duration": 368.0,
        "idle_x_start": 0.4579106271266937,
        "idle_y_start": 0.1320219337940216,
        "driver_idx": 88.0,
        "idle_start_subblock_id": 4.0
    },
    {
        "idle_start_timestamp": 660.0,
        "idle_duration": 1440.0,
        "idle_x_start": 0.03847047686576843,
        "idle_y_start": 0.6358058452606201,
        "driver_idx": 89.0,
        "idle_start_subblock_id": 2.0
    },
    {
        "idle_start_timestamp": 840.0,
        "idle_duration": 304.0,
        "idle_x_start": 0.6150857210159302,
        "idle_y_start": 0.31644535064697266,
        "driver_idx": 90.0,
        "idle_start_subblock_id": 9.0
    },
    {
        "idle_start_timestamp": 1020.0,
        "idle_duration": 287.0,
        "idle_x_start": 0.7867715358734131,
        "idle_y_start": 0.9670631885528564,
        "driver_idx": 91.0,
        "idle_start_subblock_id": 15.0
    },
    {
        "idle_start_timestamp": 660.0,
        "idle_duration": 314.0,
        "idle_x_start": 0.9314795136451721,
        "idle_y_start": 0.7949178814888,
        "driver_idx": 92.0,
        "idle_start_subblock_id": 15.0
    },
    {
        "idle_start_timestamp": 1080.0,
        "idle_duration": 227.0,
        "idle_x_start": 0.16258202493190765,
        "idle_y_start": 0.10012796521186829,
        "driver_idx": 93.0,
        "idle_start_subblock_id": 0.0
    },
    {
        "idle_start_timestamp": 780.0,
        "idle_duration": 262.0,
        "idle_x_start": 0.11483658850193024,
        "idle_y_start": 0.5726771354675293,
        "driver_idx": 94.0,
        "idle_start_subblock_id": 2.0
    },
    {
        "idle_start_timestamp": 120.0,
        "idle_duration": 382.0,
        "idle_x_start": 0.3080625534057617,
        "idle_y_start": 0.8184199333190918,
        "driver_idx": 95.0,
        "idle_start_subblock_id": 7.0
    },
    {
        "idle_start_timestamp": 1140.0,
        "idle_duration": 132.0,
        "idle_x_start": 0.2070353925228119,
        "idle_y_start": 0.19103658199310303,
        "driver_idx": 96.0,
        "idle_start_subblock_id": 0.0
    },
    {
        "idle_start_timestamp": 660.0,
        "idle_duration": 345.0,
        "idle_x_start": 0.5330185890197754,
        "idle_y_start": 0.44474363327026367,
        "driver_idx": 97.0,
        "idle_start_subblock_id": 9.0
    },
    {
        "idle_start_timestamp": 420.0,
        "idle_duration": 416.0,
        "idle_x_start": 0.6999956369400024,
        "idle_y_start": 0.9782813787460327,
        "driver_idx": 98.0,
        "idle_start_subblock_id": 11.0
    },
    {
        "idle_start_timestamp": 1320.0,
        "idle_duration": 559.0,
        "idle_x_start": 0.8521929979324341,
        "idle_y_start": 0.15476056933403015,
        "driver_idx": 99.0,
        "idle_start_subblock_id": 12.0
    }
]